TPM2PPF_learntools/__init__.py
TPM2PPF_learntools/TPM2/__init__.py
TPM2PPF_learntools/TPM2/ex1.py
TPM2PPF_learntools/TPM2/ex2.py
TPM2PPF_learntools/TPM2/ex3.py
TPM2PPF_learntools/core/__init__.py
TPM2PPF_learntools/core/asserts.py
TPM2PPF_learntools/core/colors.py
TPM2PPF_learntools/core/constants.py
TPM2PPF_learntools/core/exceptions.py
TPM2PPF_learntools/core/globals_binder.py
TPM2PPF_learntools/core/multiproblem.py
TPM2PPF_learntools/core/problem.py
TPM2PPF_learntools/core/problem_view.py
TPM2PPF_learntools/core/richtext.py
TPM2PPF_learntools/core/tracking.py
TPM2PPF_learntools/core/utils.py
TPM2PPF_learntools/python/__init__.py
TPM2PPF_learntools/python/blackjack.py
TPM2PPF_learntools/python/ex1.py
TPM2PPF_learntools/python/ex2.py
TPM2PPF_learntools/python/ex3.py
TPM2PPF_learntools/python/ex4.py
TPM2PPF_learntools/python/ex5.py
TPM2PPF_learntools/python/ex6.py
TPM2PPF_learntools/python/ex7.py
TPM2PPF_learntools/python/jimmy_slots.py
TPM2PPF_learntools/python/luigi_analysis.py
TPM2PPF_learntools/python/quickdraw.py
TPM2PPF_learntools/python/roulette.py
TPM2PPF_learntools/python/solns/__init__.py
TPM2PPF_learntools/python/solns/blackjack_gt.py
TPM2PPF_learntools/python/solns/diamond.py
TPM2PPF_learntools/python/solns/jimmygraph.py
TPM2PPF_learntools/python/solns/multi_word_search.py
TPM2PPF_learntools/python/solns/roulette_analysis.py
TPM2PPF_learntools/python/solns/word_search.py
TPM2PPF_learntools-0.1.2.dist-info/LICENSE
TPM2PPF_learntools-0.1.2.dist-info/METADATA
TPM2PPF_learntools-0.1.2.dist-info/WHEEL
TPM2PPF_learntools-0.1.2.dist-info/top_level.txt
TPM2PPF_learntools-0.1.2.dist-info/zip-safe
TPM2PPF_learntools-0.1.2.dist-info/RECORD
